configman/__init__.py
configman/configman.py
configman/exceptions.py
configman/py.typed
config_man-0.0.4.dist-info/LICENSE
config_man-0.0.4.dist-info/METADATA
config_man-0.0.4.dist-info/WHEEL
config_man-0.0.4.dist-info/top_level.txt
config_man-0.0.4.dist-info/zip-safe
config_man-0.0.4.dist-info/RECORD
