Metadata-Version: 2.1
Name: config-man
Version: 0.0.4
Summary: An easy Python configuration manager with Typing support.
Home-page: https://github.com/mmohaveri/config-man
Author: Mahdi Mohaveri
Author-email: mmohaveri@gmail.com
License: MIT License
Keywords: development configuration
Platform: UNKNOWN
Classifier: Development Status :: 3 - Alpha
Classifier: Intended Audience :: Developers
Classifier: License :: OSI Approved :: MIT License
Classifier: Operating System :: OS Independent
Classifier: Programming Language :: Python :: 3 :: Only
Classifier: Programming Language :: Python :: 3.5
Classifier: Programming Language :: Python :: 3.6
Classifier: Programming Language :: Python :: 3.7
Classifier: Programming Language :: Python :: 3.8
Classifier: Topic :: Software Development
Classifier: Topic :: Utilities
Classifier: Typing :: Typed
Requires-Python: >=3.6
Requires-Dist: glom (>=19.10.0)
